micropython_motor/__init__.py
micropython_motor/motor.py
micropython_motor/servo.py
micropython_motor/stepper.py
micropython_motor-0.2.0.dist-info/LICENSE
micropython_motor-0.2.0.dist-info/METADATA
micropython_motor-0.2.0.dist-info/WHEEL
micropython_motor-0.2.0.dist-info/top_level.txt
micropython_motor-0.2.0.dist-info/RECORD
