Metadata-Version: 2.1
Name: micropython-motor
Version: 0.2.0
Summary: MicroPython Helpers for controlling PWM based motors and servos 
Author-email: JDM <xxyx@mailmeto.mozmail.com>
License: MIT
Project-URL: Homepage, https://github.com/jposada202020/MicroPython_MOTOR
Keywords: sensor,micropython,motor,pwm,motor,servo,drv8833,stepper
Classifier: Intended Audience :: Developers
Classifier: Topic :: Software Development :: Libraries
Classifier: Topic :: Software Development :: Embedded Systems
Classifier: Topic :: System :: Hardware
Classifier: License :: OSI Approved :: MIT License
Classifier: Programming Language :: Python :: Implementation :: MicroPython
License-File: LICENSE
